getallcolumnname/__init__.py
getallcolumnname-0.2.dist-info/METADATA
getallcolumnname-0.2.dist-info/WHEEL
getallcolumnname-0.2.dist-info/top_level.txt
getallcolumnname-0.2.dist-info/RECORD
