Metadata-Version: 2.1
Name: getallcolumnname
Version: 0.2
Summary: getallcolumns
Author: srini
Keywords: python,pyspark,catalog,schema,hive_metastore
Classifier: Development Status :: 1 - Planning
Classifier: Intended Audience :: Developers
Classifier: Programming Language :: Python :: 3
Classifier: Operating System :: Unix
Classifier: Operating System :: MacOS :: MacOS X
Classifier: Operating System :: Microsoft :: Windows
